[
  {
    "id": "ae837468-98ef-449e-b66b-d0b904f25d8e",
    "data": [
      {
        "text": "i do",
        "userDefined": false
      }
    ],
    "isTemplate": false,
    "count": 0,
    "updated": 1524564593
  },
  {
    "id": "58c1d83d-ae88-4905-a8ef-4a0c5027eba1",
    "data": [
      {
        "text": "it is amazing",
        "userDefined": false
      }
    ],
    "isTemplate": false,
    "count": 0,
    "updated": 1524564593
  },
  {
    "id": "23540ca3-8720-4cc2-b87e-fc1ca0d3995a",
    "data": [
      {
        "text": "i like it",
        "userDefined": false
      }
    ],
    "isTemplate": false,
    "count": 0,
    "updated": 1524564593
  },
  {
    "id": "a29592d4-ad58-47d7-a34f-74069b7913e7",
    "data": [
      {
        "text": "yes",
        "userDefined": false
      }
    ],
    "isTemplate": false,
    "count": 0,
    "updated": 1524564593
  },
  {
    "id": "d83b2bdc-4fe8-4c0d-b252-c31a14dba979",
    "data": [
      {
        "text": "i love it",
        "userDefined": false
      }
    ],
    "isTemplate": false,
    "count": 0,
    "updated": 1524564593
  }
]